sdm_ore/__init__.py
sdm_ore/install_asset.py
sdm_ore-0.1.0.dist-info/METADATA
sdm_ore-0.1.0.dist-info/WHEEL
sdm_ore-0.1.0.dist-info/entry_points.txt
sdm_ore-0.1.0.dist-info/top_level.txt
sdm_ore-0.1.0.dist-info/RECORD
